CacheToolsUtils.py
cachetoolsutils-10.4.dist-info/LICENSE
cachetoolsutils-10.4.dist-info/METADATA
cachetoolsutils-10.4.dist-info/WHEEL
cachetoolsutils-10.4.dist-info/top_level.txt
cachetoolsutils-10.4.dist-info/RECORD
