Metadata-Version: 2.2
Name: CacheToolsUtils
Version: 10.4
Summary: Cachetools Utilities
Author-email: Fabien Coelho <cachetools.utils@coelho.net>
License: CC0
Project-URL: repository, https://github.com/zx80/cachetools-utils
Project-URL: documentation, https://zx80.github.io/cachetools-utils/
Project-URL: issues, https://github.com/zx80/cachetools-utils/issues
Project-URL: package, https://pypi.org/project/CacheToolsUtils/
Classifier: Development Status :: 5 - Production/Stable
Classifier: Intended Audience :: Developers
Classifier: License :: CC0 1.0 Universal (CC0 1.0) Public Domain Dedication
Classifier: Programming Language :: Python
Classifier: Topic :: Software Development :: Libraries :: Python Modules
Requires-Python: >=3.10
License-File: LICENSE
Requires-Dist: cachetools
Provides-Extra: dev
Requires-Dist: mypy; extra == "dev"
Requires-Dist: pyright; extra == "dev"
Requires-Dist: black; extra == "dev"
Requires-Dist: flake8; extra == "dev"
Requires-Dist: ruff; extra == "dev"
Requires-Dist: pytest; extra == "dev"
Requires-Dist: coverage; extra == "dev"
Requires-Dist: pymarkdownlnt; extra == "dev"
Provides-Extra: doc
Requires-Dist: sphinx; extra == "doc"
Requires-Dist: sphinx_rtd_theme; extra == "doc"
Requires-Dist: sphinx-autoapi; extra == "doc"
Requires-Dist: sphinx-lint; extra == "doc"
Requires-Dist: myst_parser; extra == "doc"
Provides-Extra: crypt
Requires-Dist: pycryptodome; extra == "crypt"
Provides-Extra: tests
Requires-Dist: pymemcache; extra == "tests"
Requires-Dist: redis; extra == "tests"
Provides-Extra: pub
Requires-Dist: build; extra == "pub"
Requires-Dist: wheel; extra == "pub"
Requires-Dist: twine; extra == "pub"
